swissqr/__init__.py
swissqr/exceptions.py
swissqr/paymentparty.py
swissqr/qr.py
swissqr/qrdata.py
swissqr-0.2.0.dist-info/METADATA
swissqr-0.2.0.dist-info/WHEEL
swissqr-0.2.0.dist-info/top_level.txt
swissqr-0.2.0.dist-info/RECORD
