Metadata-Version: 2.1
Name: swissqr
Version: 0.2.0
Summary: Generator for SwissQR invoice qr codes
Home-page: https://gitlab.com/dinuthehuman/swissqr
Author: Martin Obrist
Author-email: dev@obrist.email
License: MIT
Project-URL: Source Code, https://gitlab.com/dinuthehuman/swissqr
Project-URL: Issue Tracker, https://gitlab.com/dinuthehuman/swissqr/-/issues
Keywords: Switzerland,payment,qrcode
Classifier: Development Status :: 4 - Beta
Classifier: License :: OSI Approved :: MIT License
Classifier: Topic :: Office/Business :: Financial
Classifier: Operating System :: OS Independent
Classifier: Programming Language :: Python :: 3
Classifier: Programming Language :: Python :: 3 :: Only
Requires-Python: >=3.9, <4
Requires-Dist: beautifulsoup4
Requires-Dist: iso4217
Requires-Dist: lxml
Requires-Dist: pyban
Requires-Dist: pyban-swift
Requires-Dist: pycountry
Requires-Dist: pydantic
Requires-Dist: qrcode
Provides-Extra: dev
Requires-Dist: invoke ; extra == 'dev'
Requires-Dist: twine ; extra == 'dev'
